<?xml version = '1.0' encoding = 'UTF-8'?>
<Relation class="oracle.dbtools.crest.model.design.logical.Relation" name="resulta" directorySegmentName="seg_0" id="AE3E6C36-242D-5A75-D41D-863308F014CB">
<createdBy>User</createdBy>
<createdTime>2021-12-02 17:14:24 UTC</createdTime>
<ownerDesignName>mojon</ownerDesignName>
<engineerTo>
<item key="53A23283-2CC0-01DE-B23B-D59D8A0D1DE2" value="true"/>
</engineerTo>
<sourcePk>6219B7D1-2B3A-CC7C-52B3-127009BBD66B</sourcePk>
<identifying>false</identifying>
<optionalSource>true</optionalSource>
<optionalTarget>false</optionalTarget>
<sourceCardinality>1</sourceCardinality>
<sourceEntity>FCB922D0-A627-514E-B966-FEAD08F25471</sourceEntity>
<targetCardinalityString>*</targetCardinalityString>
<targetEntity>185B0A5A-97C3-F5A6-FB05-6D644FEF638E</targetEntity>
<transferable>true</transferable>
<deleteRule>NO ACTION</deleteRule>
</Relation>
